pytest_playwright_artifacts/__init__.py
pytest_playwright_artifacts/plugin.py
pytest_playwright_artifacts-0.1.0.dist-info/WHEEL
pytest_playwright_artifacts-0.1.0.dist-info/entry_points.txt
pytest_playwright_artifacts-0.1.0.dist-info/METADATA
pytest_playwright_artifacts-0.1.0.dist-info/RECORD
