Metadata-Version: 2.3
Name: pytest-playwright-artifacts
Version: 0.1.0
Summary: Pytest plugin that captures HTML, screenshots, and console logs on Playwright test failures
Keywords: pytest,playwright,testing,artifacts
Author: Michael Bianco
Author-email: Michael Bianco <mike@mikebian.co>
Requires-Dist: structlog-config>=0.6.0
Requires-Dist: playwright>=1.40.0
Requires-Python: >=3.11
Project-URL: Repository, https://github.com/iloveitaly/pytest-playwright-artifacts
